bot_bot/__init__.py
bot_bot/__main__.py
bot_bot/actions.py
bot_bot/bot.py
bot_bot/main_view.py
bot_bot/main_view.pytoui
Bot_Minecraft-0.3.0.dist-info/METADATA
Bot_Minecraft-0.3.0.dist-info/WHEEL
Bot_Minecraft-0.3.0.dist-info/entry_points.txt
Bot_Minecraft-0.3.0.dist-info/top_level.txt
Bot_Minecraft-0.3.0.dist-info/RECORD
