Metadata-Version: 2.1
Name: Bot-Minecraft
Version: 0.3.0
Summary: Uma biblioteca de bots para Minecraft com mineração e combate automático
Home-page: UNKNOWN
Author: Guilherme
Author-email: h31365202@icloud.com
License: UNKNOWN
Platform: UNKNOWN
Classifier: Programming Language :: Python :: 3
Classifier: License :: OSI Approved :: MIT License
Classifier: Operating System :: OS Independent
Requires-Python: >=3.6
Requires-Dist: minecraft==0.1.2
